retromol/__init__.py
retromol/cli.py
retromol/version.py
retromol/chem/__init__.py
retromol/chem/fingerprint.py
retromol/chem/masking.py
retromol/chem/matching.py
retromol/chem/mol.py
retromol/chem/reaction.py
retromol/chem/tagging.py
retromol/chem/valence.py
retromol/data/__init__.py
retromol/data/mxn_other.yml
retromol/data/mxn_pks.yml
retromol/data/mxn_pks_chiral.yml
retromol/data/rxn.yml
retromol/fingerprint/__init__.py
retromol/fingerprint/fingerprint.py
retromol/fingerprint/monomer_collapse.py
retromol/fingerprint/similarity.py
retromol/io/__init__.py
retromol/io/json.py
retromol/io/streaming.py
retromol/model/__init__.py
retromol/model/assembly_graph.py
retromol/model/identity.py
retromol/model/reaction_graph.py
retromol/model/readout.py
retromol/model/result.py
retromol/model/rules.py
retromol/model/submission.py
retromol/model/synthesis.py
retromol/pipelines/__init__.py
retromol/pipelines/parsing.py
retromol/utils/__init__.py
retromol/utils/hashing.py
retromol/utils/logging.py
retromol/utils/timeout.py
retromol/visualization/__init__.py
retromol/visualization/reaction_graph.py
retromol-2.2.2.dist-info/METADATA
retromol-2.2.2.dist-info/WHEEL
retromol-2.2.2.dist-info/entry_points.txt
retromol-2.2.2.dist-info/licenses/LICENSE
retromol-2.2.2.dist-info/RECORD
