Metadata-Version: 2.4
Name: retromol
Version: 2.2.2
Summary: RetroMol is retrosynthetic analysis tool for modular natural products
Project-URL: Homepage, https://github.com/moltools/retromol
Project-URL: Repository, https://github.com/moltools/retromol
Project-URL: Issues, https://github.com/moltools/retromol/issues
Project-URL: Documentation, https://github.com/moltools/retromol#readme
Author-email: David Meijer <david.meijer@wur.nl>
License-Expression: MIT
License-File: LICENSE
Keywords: biosynthesis,monomers,natural-products,retrobiosynthesis
Classifier: Development Status :: 5 - Production/Stable
Classifier: Intended Audience :: Science/Research
Classifier: License :: OSI Approved :: MIT License
Classifier: Programming Language :: Python
Classifier: Programming Language :: Python :: 3
Classifier: Programming Language :: Python :: 3.10
Classifier: Programming Language :: Python :: 3.11
Classifier: Programming Language :: Python :: 3.12
Classifier: Topic :: Scientific/Engineering :: Bio-Informatics
Requires-Python: >=3.10
Requires-Dist: ijson
Requires-Dist: matplotlib
Requires-Dist: networkx==3.2.1
Requires-Dist: numpy
Requires-Dist: pandas
Requires-Dist: pyyaml
Requires-Dist: rdkit==2025.9.1
Requires-Dist: tqdm
Provides-Extra: dev
Requires-Dist: pytest; extra == 'dev'
